django_replicated/__init__.py
django_replicated/dbchecker.py
django_replicated/decorators.py
django_replicated/middleware.py
django_replicated/router.py
django_replicated/router_multidb.py
django_replicated/router_multimaster.py
django_replicated/router_syncslave.py
django_replicated/settings.py
django_replicated/utils.py
django_replicated_ext-3.1.dist-info/METADATA
django_replicated_ext-3.1.dist-info/RECORD
django_replicated_ext-3.1.dist-info/WHEEL
django_replicated_ext-3.1.dist-info/top_level.txt
